pydro/_version.py
pydro/__init__.py
pydro/pydro.pypy38-pp73-x86-linux-gnu.so
pydro-0.1.2.dist-info/METADATA
pydro-0.1.2.dist-info/WHEEL
pydro-0.1.2.dist-info/top_level.txt
pydro-0.1.2.dist-info/LICENSE.txt
pydro-0.1.2.dist-info/RECORD
