Metadata-Version: 2.1
Name: pydro
Version: 0.1.2
Summary: Hydrological modelling in Python
Author: David Brochart
Author-email: david.brochart@gmail.com
License-File: LICENSE.txt
